PyPNA/PyPNA.py
PyPNA/__init__.py
PyPNA-0.1.6.dist-info/LICENSE
PyPNA-0.1.6.dist-info/METADATA
PyPNA-0.1.6.dist-info/WHEEL
PyPNA-0.1.6.dist-info/top_level.txt
PyPNA-0.1.6.dist-info/RECORD
