Metadata-Version: 2.1
Name: PyPNA
Version: 0.1.6
Summary: Python interface for Keysight PNA
Home-page: https://github.com/Bryce-AC/PyPNA
Author: Bryce Chung
Author-email: bryce.chung@adelaide.edu.au
License: GPLv3
Platform: UNKNOWN
Classifier: Programming Language :: Python :: 3.9
License-File: LICENSE
Requires-Dist: pyvisa
Requires-Dist: matplotlib
Requires-Dist: numpy
